{
  "calls": [
    {
      "agency": "Example Home Health Agency 1",
      "phone": "+15551234567",
      "timestamp": "2025-04-08T03:58:22.999958",
      "status": "error",
      "response": "HTTP 400 error: Unable to create record: The number +15551234567 is unverified. Trial accounts may only make calls to verified numbers."
    },
    {
      "agency": "Example Home Health Agency 2",
      "phone": "+15557654321",
      "timestamp": "2025-04-08T03:58:25.096343",
      "status": "error",
      "response": "HTTP 400 error: Unable to create record: The number +15557654321 is unverified. Trial accounts may only make calls to verified numbers."
    }
  ]
}